syscon_clickplc/__init__.py
syscon_clickplc/driver.py
syscon_clickplc/mock.py
syscon_clickplc/util.py
syscon_clickplc-0.0.5.dist-info/LICENSE
syscon_clickplc-0.0.5.dist-info/METADATA
syscon_clickplc-0.0.5.dist-info/WHEEL
syscon_clickplc-0.0.5.dist-info/entry_points.txt
syscon_clickplc-0.0.5.dist-info/top_level.txt
syscon_clickplc-0.0.5.dist-info/RECORD
