Metadata-Version: 2.1
Name: syscon_clickplc
Version: 0.0.5
Summary: Python driver for Koyo Ethernet ClickPLCs.
Home-page: https://github.com/SYSCON-International/syscon_clickplc
Author: Patrick Fuller
Author-email: pat@numat-tech.com
Maintainer: SYSCON International
Maintainer-email: dev@syscon-intl.com
License: GPLv2
Classifier: License :: OSI Approved :: GNU General Public License v2 (GPLv2)
Classifier: Development Status :: 4 - Beta
Classifier: Natural Language :: English
Classifier: Programming Language :: Python
Classifier: Programming Language :: Python :: 3
Classifier: Programming Language :: Python :: 3.8
Classifier: Programming Language :: Python :: 3.9
Classifier: Programming Language :: Python :: 3.10
Classifier: Programming Language :: Python :: 3.11
Classifier: Programming Language :: Python :: 3.12
Classifier: Topic :: Scientific/Engineering :: Human Machine Interfaces
License-File: LICENSE
Requires-Dist: pymodbus >=2.4.0 ; python_version == "3.8"
Requires-Dist: pymodbus >=2.4.0 ; python_version == "3.9"
Requires-Dist: pymodbus <3.7.0,>=3.0.2 ; python_version >= "3.10"
Provides-Extra: test
Requires-Dist: pytest ; extra == 'test'
Requires-Dist: pytest-cov ; extra == 'test'
Requires-Dist: pytest-asyncio ; extra == 'test'
Requires-Dist: mypy ==1.10.0 ; extra == 'test'
Requires-Dist: ruff ==0.4.2 ; extra == 'test'
